anomaly_devosmita/__init__.py
anomaly_devosmita/anomaly_data_preprocessing.py
anomaly_devosmita/anomaly_detection.py
anomaly_devosmita/anomaly_libs.py
anomaly_devosmita/anomaly_main.py
anomaly_devosmita/anomaly_models.py
anomaly_devosmita-0.0.7.dist-info/LICENSE
anomaly_devosmita-0.0.7.dist-info/METADATA
anomaly_devosmita-0.0.7.dist-info/WHEEL
anomaly_devosmita-0.0.7.dist-info/top_level.txt
anomaly_devosmita-0.0.7.dist-info/RECORD
